versatOutput/hardware/Merge2.v
`timescale 1ns / 1ps

module Merge2 #(
   parameter DELAY_W = 7,
   parameter DATA_W  = 32
) (
   //control
   input clk,
   input rst,

   input running,
   input run,

   //input / output data
                             input [DATA_W-1:0] in0,
   (* versat_latency = 1 *)  input [DATA_W-1:0] in1,
   (* versat_latency = 2 *)  input [DATA_W-1:0] in2,
   (* versat_latency = 3 *)  input [DATA_W-1:0] in3,
   (* versat_latency = 4 *)  input [DATA_W-1:0] in4,
   (* versat_latency = 5 *)  input [DATA_W-1:0] in5,
   (* versat_latency = 6 *)  input [DATA_W-1:0] in6,
   (* versat_latency = 7 *)  input [DATA_W-1:0] in7,
   (* versat_latency = 8 *)  input [DATA_W-1:0] in8,
   (* versat_latency = 9 *)  input [DATA_W-1:0] in9,
   (* versat_latency = 10 *) input [DATA_W-1:0] in10,
   (* versat_latency = 11 *) input [DATA_W-1:0] in11,
   (* versat_latency = 12 *) input [DATA_W-1:0] in12,
   (* versat_latency = 13 *) input [DATA_W-1:0] in13,
   (* versat_latency = 14 *) input [DATA_W-1:0] in14,
   (* versat_latency = 15 *) input [DATA_W-1:0] in15,
   (* versat_latency = 16 *) input [DATA_W-1:0] in16,
   (* versat_latency = 17 *) input [DATA_W-1:0] in17,
   (* versat_latency = 18 *) input [DATA_W-1:0] in18,
   (* versat_latency = 19 *) input [DATA_W-1:0] in19,
   (* versat_latency = 20 *) input [DATA_W-1:0] in20,
   (* versat_latency = 21 *) input [DATA_W-1:0] in21,
   (* versat_latency = 22 *) input [DATA_W-1:0] in22,
   (* versat_latency = 23 *) input [DATA_W-1:0] in23,
   (* versat_latency = 24 *) input [DATA_W-1:0] in24,
   (* versat_latency = 25 *) input [DATA_W-1:0] in25,
   (* versat_latency = 26 *) input [DATA_W-1:0] in26,
   (* versat_latency = 27 *) input [DATA_W-1:0] in27,
   (* versat_latency = 28 *) input [DATA_W-1:0] in28,
   (* versat_latency = 29 *) input [DATA_W-1:0] in29,
   (* versat_latency = 30 *) input [DATA_W-1:0] in30,
   (* versat_latency = 31 *) input [DATA_W-1:0] in31,

   (* versat_latency = 1 *) output reg [DATA_W-1:0] out0,

   input [DELAY_W-1:0] delay0
);

   reg  [DELAY_W-1:0] delay;

   wire [ DATA_W-1:0] select[31:0];

   assign select[0]  = in0;
   assign select[1]  = in1;
   assign select[2]  = in2;
   assign select[3]  = in3;
   assign select[4]  = in4;
   assign select[5]  = in5;
   assign select[6]  = in6;
   assign select[7]  = in7;
   assign select[8]  = in8;
   assign select[9]  = in9;
   assign select[10] = in10;
   assign select[11] = in11;
   assign select[12] = in12;
   assign select[13] = in13;
   assign select[14] = in14;
   assign select[15] = in15;
   assign select[16] = in16;
   assign select[17] = in17;
   assign select[18] = in18;
   assign select[19] = in19;
   assign select[20] = in20;
   assign select[21] = in21;
   assign select[22] = in22;
   assign select[23] = in23;
   assign select[24] = in24;
   assign select[25] = in25;
   assign select[26] = in26;
   assign select[27] = in27;
   assign select[28] = in28;
   assign select[29] = in29;
   assign select[30] = in30;
   assign select[31] = in31;

   reg [4:0] counter;

   always @(posedge clk, posedge rst) begin
      if (rst) begin
         delay   <= {DELAY_W{1'b0}};
         counter <= 5'b0;
      end else if (run) begin
         delay   <= delay0;
         counter <= 5'b0;
      end else if (running) begin
         if (|delay) begin
            delay <= delay - 1;
         end

         if (delay == 0) begin
            counter <= counter + 1;
         end

         out0 <= select[counter];
      end else begin
         delay   <= delay;
         counter <= counter;
      end
   end

endmodule

versatOutput/Merge2_tb.v
`timescale 1ns / 1ps

module Merge2_tb (

);
  localparam DELAY_W = 7;
  localparam DATA_W = 32;
  // Inputs
  reg [(DATA_W)-1:0] in0;
  reg [(DATA_W)-1:0] in1;
  reg [(DATA_W)-1:0] in2;
  reg [(DATA_W)-1:0] in3;
  reg [(DATA_W)-1:0] in4;
  reg [(DATA_W)-1:0] in5;
  reg [(DATA_W)-1:0] in6;
  reg [(DATA_W)-1:0] in7;
  reg [(DATA_W)-1:0] in8;
  reg [(DATA_W)-1:0] in9;
  reg [(DATA_W)-1:0] in10;
  reg [(DATA_W)-1:0] in11;
  reg [(DATA_W)-1:0] in12;
  reg [(DATA_W)-1:0] in13;
  reg [(DATA_W)-1:0] in14;
  reg [(DATA_W)-1:0] in15;
  reg [(DATA_W)-1:0] in16;
  reg [(DATA_W)-1:0] in17;
  reg [(DATA_W)-1:0] in18;
  reg [(DATA_W)-1:0] in19;
  reg [(DATA_W)-1:0] in20;
  reg [(DATA_W)-1:0] in21;
  reg [(DATA_W)-1:0] in22;
  reg [(DATA_W)-1:0] in23;
  reg [(DATA_W)-1:0] in24;
  reg [(DATA_W)-1:0] in25;
  reg [(DATA_W)-1:0] in26;
  reg [(DATA_W)-1:0] in27;
  reg [(DATA_W)-1:0] in28;
  reg [(DATA_W)-1:0] in29;
  reg [(DATA_W)-1:0] in30;
  reg [(DATA_W)-1:0] in31;
  // Outputs
  wire [(DATA_W)-1:0] out0;
  // Control
  reg [(1)-1:0] running;
  reg [(1)-1:0] run;
  reg [(1)-1:0] clk;
  reg [(1)-1:0] rst;
  // Delays
  reg [(DELAY_W)-1:0] delay0;

  localparam CLOCK_PERIOD = 10;

  initial clk = 0;
  always #(CLOCK_PERIOD/2) clk = ~clk;
  `define ADVANCE @(posedge clk) #(CLOCK_PERIOD/2);

  Merge2 #(
    .DELAY_W(DELAY_W),
    .DATA_W(DATA_W)
  ) uut (
    .in0(in0),
    .in1(in1),
    .in2(in2),
    .in3(in3),
    .in4(in4),
    .in5(in5),
    .in6(in6),
    .in7(in7),
    .in8(in8),
    .in9(in9),
    .in10(in10),
    .in11(in11),
    .in12(in12),
    .in13(in13),
    .in14(in14),
    .in15(in15),
    .in16(in16),
    .in17(in17),
    .in18(in18),
    .in19(in19),
    .in20(in20),
    .in21(in21),
    .in22(in22),
    .in23(in23),
    .in24(in24),
    .in25(in25),
    .in26(in26),
    .in27(in27),
    .in28(in28),
    .in29(in29),
    .in30(in30),
    .in31(in31),
    .out0(out0),
    .running(running),
    .run(run),
    .clk(clk),
    .rst(rst),
    .delay0(delay0)
  );


  localparam SIM_TIME_NO_DONE = 10;
  integer i;
  task RunAccelerator;
  begin
    run = 1;

    `ADVANCE;

    run = 0;
    running = 1;

    `ADVANCE;

    for(i = 0 ; i < SIM_TIME_NO_DONE ; i = i + 1) begin
      `ADVANCE;
    end
    running = 0;
  end
  endtask

  initial begin
    `ifdef VCD;
    $dumpfile("uut.vcd");
    $dumpvars();
    `endif // VCD;
    in0 = 0;
    in1 = 0;
    in2 = 0;
    in3 = 0;
    in4 = 0;
    in5 = 0;
    in6 = 0;
    in7 = 0;
    in8 = 0;
    in9 = 0;
    in10 = 0;
    in11 = 0;
    in12 = 0;
    in13 = 0;
    in14 = 0;
    in15 = 0;
    in16 = 0;
    in17 = 0;
    in18 = 0;
    in19 = 0;
    in20 = 0;
    in21 = 0;
    in22 = 0;
    in23 = 0;
    in24 = 0;
    in25 = 0;
    in26 = 0;
    in27 = 0;
    in28 = 0;
    in29 = 0;
    in30 = 0;
    in31 = 0;
    running = 0;
    run = 0;
    clk = 0;
    rst = 0;
    delay0 = 0;

    `ADVANCE;

    rst = 1;

    `ADVANCE;

    rst = 0;

    `ADVANCE;

    // Insert logic after this point

    RunAccelerator();

    `ADVANCE;

    RunAccelerator();

    `ADVANCE;

    $finish();
  end


endmodule

versatOutput/uut.vcd
$date
	Mon Oct  6 12:12:43 2025
$end
$version
	Icarus Verilog
$end
$timescale
	1ps
$end
$scope module Merge2_tb $end
$var wire 32 ! out0 [31:0] $end
$var reg 1 " clk $end
$var reg 7 # delay0 [6:0] $end
$var reg 32 $ in0 [31:0] $end
$var reg 32 % in1 [31:0] $end
$var reg 32 & in10 [31:0] $end
$var reg 32 ' in11 [31:0] $end
$var reg 32 ( in12 [31:0] $end
$var reg 32 ) in13 [31:0] $end
$var reg 32 * in14 [31:0] $end
$var reg 32 + in15 [31:0] $end
$var reg 32 , in16 [31:0] $end
$var reg 32 - in17 [31:0] $end
$var reg 32 . in18 [31:0] $end
$var reg 32 / in19 [31:0] $end
$var reg 32 0 in2 [31:0] $end
$var reg 32 1 in20 [31:0] $end
$var reg 32 2 in21 [31:0] $end
$var reg 32 3 in22 [31:0] $end
$var reg 32 4 in23 [31:0] $end
$var reg 32 5 in24 [31:0] $end
$var reg 32 6 in25 [31:0] $end
$var reg 32 7 in26 [31:0] $end
$var reg 32 8 in27 [31:0] $end
$var reg 32 9 in28 [31:0] $end
$var reg 32 : in29 [31:0] $end
$var reg 32 ; in3 [31:0] $end
$var reg 32 < in30 [31:0] $end
$var reg 32 = in31 [31:0] $end
$var reg 32 > in4 [31:0] $end
$var reg 32 ? in5 [31:0] $end
$var reg 32 @ in6 [31:0] $end
$var reg 32 A in7 [31:0] $end
$var reg 32 B in8 [31:0] $end
$var reg 32 C in9 [31:0] $end
$var reg 1 D rst $end
$var reg 1 E run $end
$var reg 1 F running $end
$var integer 32 G i [31:0] $end
$scope module uut $end
$var wire 1 " clk $end
$var wire 7 H delay0 [6:0] $end
$var wire 32 I in0 [31:0] $end
$var wire 32 J in1 [31:0] $end
$var wire 32 K in10 [31:0] $end
$var wire 32 L in11 [31:0] $end
$var wire 32 M in12 [31:0] $end
$var wire 32 N in13 [31:0] $end
$var wire 32 O in14 [31:0] $end
$var wire 32 P in15 [31:0] $end
$var wire 32 Q in16 [31:0] $end
$var wire 32 R in17 [31:0] $end
$var wire 32 S in18 [31:0] $end
$var wire 32 T in19 [31:0] $end
$var wire 32 U in2 [31:0] $end
$var wire 32 V in20 [31:0] $end
$var wire 32 W in21 [31:0] $end
$var wire 32 X in22 [31:0] $end
$var wire 32 Y in23 [31:0] $end
$var wire 32 Z in24 [31:0] $end
$var wire 32 [ in25 [31:0] $end
$var wire 32 \ in26 [31:0] $end
$var wire 32 ] in27 [31:0] $end
$var wire 32 ^ in28 [31:0] $end
$var wire 32 _ in29 [31:0] $end
$var wire 32 ` in3 [31:0] $end
$var wire 32 a in30 [31:0] $end
$var wire 32 b in31 [31:0] $end
$var wire 32 c in4 [31:0] $end
$var wire 32 d in5 [31:0] $end
$var wire 32 e in6 [31:0] $end
$var wire 32 f in7 [31:0] $end
$var wire 32 g in8 [31:0] $end
$var wire 32 h in9 [31:0] $end
$var wire 1 D rst $end
$var wire 1 E run $end
$var wire 1 F running $end
$var reg 5 i counter [4:0] $end
$var reg 7 j delay [6:0] $end
$var reg 32 k out0 [31:0] $end
$upscope $end
$scope task RunAccelerator $end
$upscope $end
$upscope $end
$enddefinitions $end
#0
$dumpvars
bx k
bx j
bx i
b0 h
b0 g
b0 f
b0 e
b0 d
b0 c
b0 b
b0 a
b0 `
b0 _
b0 ^
b0 ]
b0 \
b0 [
b0 Z
b0 Y
b0 X
b0 W
b0 V
b0 U
b0 T
b0 S
b0 R
b0 Q
b0 P
b0 O
b0 N
b0 M
b0 L
b0 K
b0 J
b0 I
b0 H
bx G
0F
0E
0D
b0 C
b0 B
b0 A
b0 @
b0 ?
b0 >
b0 =
b0 <
b0 ;
b0 :
b0 9
b0 8
b0 7
b0 6
b0 5
b0 4
b0 3
b0 2
b0 1
b0 0
b0 /
b0 .
b0 -
b0 ,
b0 +
b0 *
b0 )
b0 (
b0 '
b0 &
b0 %
b0 $
b0 #
0"
bx !
$end
#5000
1"
#10000
b0 i
b0 j
1D
0"
#15000
1"
#20000
0D
0"
#25000
1"
#30000
1E
0"
#35000
1"
#40000
1F
0E
0"
#45000
b0 !
b0 k
b1 i
1"
#50000
b0 G
0"
#55000
b10 i
1"
#60000
b1 G
0"
#65000
b11 i
1"
#70000
b10 G
0"
#75000
b100 i
1"
#80000
b11 G
0"
#85000
b101 i
1"
#90000
b100 G
0"
#95000
b110 i
1"
#100000
b101 G
0"
#105000
b111 i
1"
#110000
b110 G
0"
#115000
b1000 i
1"
#120000
b111 G
0"
#125000
b1001 i
1"
#130000
b1000 G
0"
#135000
b1010 i
1"
#140000
b1001 G
0"
#145000
b1011 i
1"
#150000
0F
b1010 G
0"
#155000
1"
#160000
1E
0"
#165000
b0 i
1"
#170000
1F
0E
0"
#175000
b1 i
1"
#180000
b0 G
0"
#185000
b10 i
1"
#190000
b1 G
0"
#195000
b11 i
1"
#200000
b10 G
0"
#205000
b100 i
1"
#210000
b11 G
0"
#215000
b101 i
1"
#220000
b100 G
0"
#225000
b110 i
1"
#230000
b101 G
0"
#235000
b111 i
1"
#240000
b110 G
0"
#245000
b1000 i
1"
#250000
b111 G
0"
#255000
b1001 i
1"
#260000
b1000 G
0"
#265000
b1010 i
1"
#270000
b1001 G
0"
#275000
b1011 i
1"
#280000
0F
b1010 G
0"
